{
    "content": [
        "ce1afcd117a5a2f406fba7ed01933e88\t{\"Parent\":\"UC Browser 9.6\",\"Platform_Version\":\"2.2\",\"Device_Name\":\"Galaxy S Duos\",\"Device_Maker\":\"Samsung\",\"Device_Code_Name\":\"GT-S7562\",\"Device_Brand_Name\":\"Samsung\",\"RenderingEngine_Name\":\"U2\",\"RenderingEngine_Description\":\"a WebKit Fork by UC Web\",\"RenderingEngine_Maker\":\"UCWeb Inc.\"}",
        "ce11d1a5e2cca37d98bea81bcf61399c\t{\"Parent\":\"Avant\\\/IE 8.0\",\"Browser_Bits\":\"64\",\"Platform\":\"WinVista\",\"Platform_Version\":\"6.0\",\"Platform_Description\":\"Windows Vista\",\"Platform_Bits\":\"64\",\"Platform_Maker\":\"Microsoft Corporation\",\"Win64\":true}",
        "ce124294a7d21e82a2b51dc41fcc6d97\t{\"Parent\":\"Avant\\\/IE 7.0\",\"Browser_Bits\":\"32\",\"Platform\":\"WinXP\",\"Platform_Version\":\"5.1\",\"Platform_Description\":\"Windows XP\",\"Platform_Bits\":\"32\",\"Platform_Maker\":\"Microsoft Corporation\",\"Win32\":true}",
        "ce1d8f293dd4a4d9d226525ef4559302\t{\"Parent\":\"UC Browser 2.0\",\"Platform_Version\":\"2.3\",\"JavaApplets\":true,\"RenderingEngine_Name\":\"WebKit\",\"RenderingEngine_Description\":\"For Google Chrome, iOS (including both mobile Safari, WebViews within third-party apps, and web clips), Safari, Arora, Midori, OmniWeb, Shiira, iCab since version 4, Web, SRWare Iron, Rekonq, and in Maxthon 3.\",\"RenderingEngine_Maker\":\"Apple Inc\"}",
        "ce10e361f4ab9b2914f72659df903b42\t{\"Parent\":\"Maxthon 4.0\",\"Platform\":\"Win8.1\",\"Platform_Version\":\"6.3\",\"Platform_Description\":\"Windows 8.1\"}",
        "ce1a242565f2c90d2742b5a47843bef5\t{\"Parent\":\"Comodo Dragon 31.1 (as Chrome)\",\"Device_Name\":\"Linux Desktop\",\"Device_Code_Name\":\"Linux Desktop\"}",
        "ce19bb577191bcf1f31c00e4a761d05f\t{\"Parent\":\"Comodo Dragon 36.7\",\"Platform\":\"Win8\",\"Platform_Version\":\"6.2\",\"Platform_Description\":\"Windows 8\",\"Platform_Bits\":\"64\",\"Platform_Maker\":\"Microsoft Corporation\",\"Win64\":true,\"Device_Name\":\"Windows Desktop\",\"Device_Code_Name\":\"Windows Desktop\"}",
        "ce1b19217135724e74634067edaa5885\t{\"Parent\":\"Android WebView 5.0\",\"Platform_Version\":\"2.1\",\"Device_Name\":\"SCH-I500\",\"Device_Maker\":\"Samsung\",\"Device_Pointing_Method\":\"unknown\",\"Device_Code_Name\":\"SCH-I500\",\"Device_Brand_Name\":\"Samsung\"}",
        "ce18c3ee7b474a2f9aa800b2c2f3a107\t{\"Parent\":\"Android WebView 4.3\",\"Platform_Version\":\"4.4\",\"Device_Name\":\"Galaxy S4 Mini\",\"Device_Maker\":\"Samsung\",\"Device_Code_Name\":\"GT-I9195\",\"Device_Brand_Name\":\"Samsung\"}",
        "ce16a492a3ee6f3a9947969d6174d90e\t{\"Parent\":\"Android WebView 2.0\",\"Platform_Version\":\"4.1\",\"Device_Name\":\"One Touch MPop\",\"Device_Maker\":\"Alcatel\",\"Device_Code_Name\":\"OT-5020D\",\"Device_Brand_Name\":\"Alcatel\"}",
        "ce11792d49e961ad6d0062ca064e9e45\t{\"Parent\":\"Yandex Browser 15.3\",\"Browser_Bits\":\"32\",\"Platform\":\"MacOSX\",\"Platform_Version\":\"10.8\",\"Platform_Description\":\"Mac OS X\",\"Platform_Bits\":\"32\",\"Platform_Maker\":\"Apple Inc\",\"Device_Name\":\"Macintosh\",\"Device_Maker\":\"Apple Inc\",\"Device_Code_Name\":\"Macintosh\",\"Device_Brand_Name\":\"Apple\"}",
        "ce1b0c41aeaceaee26da798df5e7c766\t{\"Parent\":\"Opera 11.64\",\"Browser_Bits\":\"32\",\"Platform\":\"Win8.1\",\"Platform_Version\":\"6.3\",\"Platform_Description\":\"Windows 8.1\",\"Platform_Bits\":\"64\",\"Platform_Maker\":\"Microsoft Corporation\",\"Win64\":true,\"Device_Name\":\"Windows Desktop\",\"Device_Code_Name\":\"Windows Desktop\"}",
        "ce1d9c3662ef43f15f0f6c68dbd42bcd\t{\"Parent\":\"Opera 9.64\",\"Browser_Bits\":\"32\",\"Platform\":\"WinNT\",\"Platform_Description\":\"Windows NT\",\"Platform_Bits\":\"32\",\"Platform_Maker\":\"Microsoft Corporation\",\"Win32\":true,\"Device_Name\":\"Windows Desktop\",\"Device_Code_Name\":\"Windows Desktop\"}",
        "ce15c9d2bd7b1dca1b27eea57b042df9\t{\"Parent\":\"Opera 7.20\",\"Browser_Bits\":\"32\",\"Platform\":\"MacPPC\",\"Platform_Description\":\"Mac OS for Power PC\",\"Platform_Bits\":\"32\",\"Platform_Maker\":\"Apple Inc\",\"Device_Name\":\"Macintosh\",\"Device_Maker\":\"Apple Inc\",\"Device_Code_Name\":\"Macintosh\",\"Device_Brand_Name\":\"Apple\"}",
        "ce1912f562b70a84f7ee60ca0ca3473d\t{\"Parent\":\"Opera 7.00\",\"Browser_Bits\":\"32\",\"Platform\":\"WinNT\",\"Platform_Version\":\"4.0\",\"Platform_Description\":\"Windows NT\",\"Platform_Bits\":\"32\",\"Platform_Maker\":\"Microsoft Corporation\",\"Win32\":true,\"Device_Name\":\"Windows Desktop\",\"Device_Code_Name\":\"Windows Desktop\"}",
        "ce159a67433684563cece1b7541177d1\t{\"Parent\":\"Opera 6.12\",\"Browser_Bits\":\"32\",\"Platform\":\"Win8.1\",\"Platform_Version\":\"6.3\",\"Platform_Description\":\"Windows 8.1\",\"Platform_Bits\":\"32\",\"Platform_Maker\":\"Microsoft Corporation\",\"Win32\":true,\"Device_Name\":\"Windows Desktop\",\"Device_Code_Name\":\"Windows Desktop\"}",
        "ce1aef8582cef4cbb0c506f25c8de86f\t{\"Parent\":\"Puffin 4.3\",\"Browser_Bits\":\"32\",\"Platform\":\"Android\",\"Platform_Version\":\"4.1\",\"Platform_Description\":\"Android OS\",\"Platform_Bits\":\"32\",\"Platform_Maker\":\"Google Inc\"}",
        "ce1c9cc0f46f84e413a40d27f7c7da8f\t{\"Parent\":\"Chrome 50.0 for Android\",\"Platform_Version\":\"4.2\",\"isTablet\":true,\"Device_Name\":\"IdeaPad A10\",\"Device_Maker\":\"Lenovo\",\"Device_Type\":\"Tablet\",\"Device_Code_Name\":\"IdeaPad A10\",\"Device_Brand_Name\":\"Lenovo\"}",
        "ce16867bd70bcbca8514383f6ac996d6\t{\"Parent\":\"Chrome 48.0 for Android\",\"Platform_Version\":\"4.3\",\"Device_Name\":\"Optimus L5\",\"Device_Maker\":\"LG\",\"Device_Code_Name\":\"E610\",\"Device_Brand_Name\":\"LG\"}",
        "ce1b3f18c464194c950385f74b31f1bb\t{\"Parent\":\"Chrome 48.0 for Android\",\"Platform_Version\":\"4.2\",\"isTablet\":true,\"Device_Name\":\"LifeTab E10312\",\"Device_Maker\":\"Medion\",\"Device_Type\":\"Tablet\",\"Device_Code_Name\":\"LifeTab E10312\",\"Device_Brand_Name\":\"Medion\"}",
        "ce186aa7760c2de4b1fe742a9b400160\t{\"Parent\":\"Chrome 48.0 for Android\",\"Platform_Version\":\"4.4\",\"Device_Name\":\"Cat B15Q\",\"Device_Maker\":\"Caterpillar\",\"Device_Code_Name\":\"B15Q\",\"Device_Brand_Name\":\"Caterpillar\"}",
        "ce1f5c18212ddc51fa33d8be667fa37c\t{\"Parent\":\"Chrome 45.0 for Android\",\"Platform_Version\":\"4.4\",\"Device_Name\":\"Moto X\",\"Device_Maker\":\"Motorola\",\"Device_Code_Name\":\"XT1058\",\"Device_Brand_Name\":\"Motorola\"}",
        "ce1c6c82817f86976a12bb04641fa6a5\t{\"Parent\":\"Chrome 37.0 for Android\",\"Platform_Version\":\"4.0\",\"Device_Name\":\"MI 2\",\"Device_Maker\":\"Xiaomi Tech\",\"Device_Pointing_Method\":\"unknown\",\"Device_Code_Name\":\"MI 2\",\"Device_Brand_Name\":\"Xiaomi\"}",
        "ce12bb1ebb7c1a48eb068cc906d4ffa2\t{\"Parent\":\"Chrome 37.0 for Android\",\"Platform_Version\":\"4.1\",\"Device_Name\":\"Vega Iron\",\"Device_Maker\":\"Pantech\",\"Device_Code_Name\":\"IM-A870L\",\"Device_Brand_Name\":\"Pantech\"}",
        "ce1b80ec2e17ce6fd584decb96894377\t{\"Parent\":\"Chrome 34.0 for Android\",\"Platform_Version\":\"4.0\"}",
        "ce11e7e39cfde61393ce7c75e2bcafde\t{\"Parent\":\"Chrome 29.0\",\"Browser_Bits\":\"32\",\"Platform\":\"WinXP\",\"Platform_Version\":\"5.2\",\"Platform_Description\":\"Windows XP\",\"Platform_Bits\":\"64\",\"Platform_Maker\":\"Microsoft Corporation\",\"Win64\":true,\"Device_Name\":\"Windows Desktop\",\"Device_Code_Name\":\"Windows Desktop\"}",
        "ce1ab0a5a1f1e1f1e8bb25a91ff68ae1\t{\"Parent\":\"Chrome 28.0 for Android\",\"Platform_Version\":\"4.3\",\"isTablet\":true,\"Device_Name\":\"Transformer Prime\",\"Device_Maker\":\"Asus\",\"Device_Type\":\"Tablet\",\"Device_Code_Name\":\"Eee Pad TF201\",\"Device_Brand_Name\":\"Asus\"}",
        "ce1af2f804a6ce33632ac81c67841d49\t{\"Parent\":\"Chrome 15.0 for iOS\",\"Platform_Version\":\"7.1\",\"Device_Name\":\"iPhone\",\"Device_Type\":\"Mobile Phone\",\"Device_Code_Name\":\"iPhone\"}",
        "ce13a3b0bff580fac5424be34c649213\t{\"Parent\":\"Microsoft Office 2016\",\"Browser_Bits\":\"32\",\"Platform\":\"Win10\",\"Platform_Version\":\"6.4\",\"Platform_Description\":\"Windows 10\",\"Platform_Bits\":\"32\",\"Platform_Maker\":\"Microsoft Corporation\",\"Win32\":true,\"RenderingEngine_Version\":\"5.0\"}",
        "ce1ea12c25bc4d2df42638ec5e32f0c1\t{\"Parent\":\"iBrowser 2.6\",\"Browser_Bits\":\"32\",\"Platform\":\"Android\",\"Platform_Version\":\"4.4\",\"Platform_Description\":\"Android OS\",\"Platform_Bits\":\"32\",\"Platform_Maker\":\"Google Inc\"}",
        "ce1af4731c0d1b9583504a4fc717c878\t{\"Parent\":\"IEMobile 6.12\",\"Device_Name\":\"Elf\",\"Device_Maker\":\"HTC\",\"Device_Code_Name\":\"Elf\",\"Device_Brand_Name\":\"HTC\"}",
        "ce1b7108b8a60a7537cc5387204712be\t{\"Parent\":\"Opera Mini 6.2\",\"Browser_Bits\":\"32\",\"Platform\":\"Android\",\"Platform_Description\":\"Android OS\",\"Platform_Bits\":\"32\",\"Platform_Maker\":\"Google Inc\",\"Device_Pointing_Method\":\"touchscreen\"}",
        "ce13db3064ef941319f5192f9a360320\t{\"Parent\":\"Epiphany 3.6\",\"Browser_Bits\":\"64\",\"Platform\":\"Ubuntu\",\"Platform_Version\":\"11.04\",\"Platform_Description\":\"Ubuntu Linux\",\"Platform_Bits\":\"64\",\"Platform_Maker\":\"Canonical Foundation\"}",
        "ce15093ab81812eaf53f29989ce21968\t{\"Parent\":\"Mobile Safari 5.0\",\"Platform_Version\":\"3.2\",\"isTablet\":true,\"Device_Name\":\"iPad\",\"Device_Type\":\"Tablet\",\"Device_Code_Name\":\"iPad\"}",
        "ce106159dc94b88bacd670fc63439a7c\t{\"Parent\":\"Lunascape 4.9\",\"Browser_Bits\":\"32\",\"Platform\":\"WinXP\",\"Platform_Version\":\"5.1\",\"Platform_Description\":\"Windows XP\",\"Platform_Bits\":\"32\",\"Platform_Maker\":\"Microsoft Corporation\",\"Win32\":true,\"JavaApplets\":true,\"Device_Name\":\"Windows Desktop\",\"Device_Code_Name\":\"Windows Desktop\",\"RenderingEngine_Name\":\"WebKit\",\"RenderingEngine_Description\":\"For Google Chrome, iOS (including both mobile Safari, WebViews within third-party apps, and web clips), Safari, Arora, Midori, OmniWeb, Shiira, iCab since version 4, Web, SRWare Iron, Rekonq, and in Maxthon 3.\",\"RenderingEngine_Maker\":\"Apple Inc\"}",
        "ce10cb9975c55606fac8f0edef9670c1\t{\"Parent\":\"Palemoon 26.0\",\"Browser_Bits\":\"32\",\"Platform\":\"Linux\",\"Platform_Description\":\"Linux\",\"Platform_Bits\":\"32\",\"Platform_Maker\":\"Linux Foundation\",\"Device_Name\":\"Linux Desktop\",\"Device_Code_Name\":\"Linux Desktop\"}",
        "ce10abd29f2773d339d22de3585de09c\t{\"Parent\":\"Palemoon Generic\",\"Browser_Bits\":\"32\",\"Platform\":\"Win10\",\"Platform_Version\":\"6.4\",\"Platform_Description\":\"Windows 10\",\"Platform_Bits\":\"64\",\"Platform_Maker\":\"Microsoft Corporation\",\"Win64\":true,\"JavaApplets\":true,\"Device_Name\":\"Windows Desktop\",\"Device_Code_Name\":\"Windows Desktop\",\"RenderingEngine_Name\":\"Goanna\",\"RenderingEngine_Description\":\"a Gecko Fork by Moonchild Productions\",\"RenderingEngine_Maker\":\"Moonchild Productions\"}",
        "ce12606ebb8807b3d987592a4229c9e8\t{\"Parent\":\"SeaMonkey 2.23\",\"Browser_Bits\":\"32\",\"Platform\":\"MacOSX\",\"Platform_Version\":\"10.7\",\"Platform_Description\":\"Mac OS X\",\"Platform_Bits\":\"32\",\"Platform_Maker\":\"Apple Inc\",\"Device_Name\":\"Macintosh\",\"Device_Maker\":\"Apple Inc\",\"Device_Code_Name\":\"Macintosh\",\"Device_Brand_Name\":\"Apple\"}",
        "ce15910a32208eb4f2824792a78374ea\t{\"Parent\":\"SeaMonkey 2.3\",\"Browser_Bits\":\"32\",\"Platform\":\"Win8\",\"Platform_Version\":\"6.2\",\"Platform_Description\":\"Windows 8\",\"Platform_Bits\":\"32\",\"Platform_Maker\":\"Microsoft Corporation\",\"Win32\":true,\"Device_Name\":\"Windows Desktop\",\"Device_Code_Name\":\"Windows Desktop\"}",
        "ce147e3308afc36f57cfd3a64197e46b\t{\"Parent\":\"Iceweasel 37.0\"}",
        "ce18cf6e72aa2a4f9adb3394b0c356dd\t{\"Parent\":\"Firefox 27.0\",\"Browser_Bits\":\"32\",\"Platform\":\"MacOSX\",\"Platform_Version\":\"10.10\",\"Platform_Description\":\"Mac OS X\",\"Platform_Bits\":\"32\",\"Platform_Maker\":\"Apple Inc\",\"Device_Name\":\"Macintosh\",\"Device_Maker\":\"Apple Inc\",\"Device_Code_Name\":\"Macintosh\",\"Device_Brand_Name\":\"Apple\"}",
        "ce1a7318f5df362b34088697e1e1b8f1\t{\"Parent\":\"PodWrangler 1.1\",\"Platform_Version\":\"4.0\"}"
    ]
}