{
    "content": [
        "f3264a97b1e504ae0f6996a657d1275e\t{\"Parent\":\"NewsGator\",\"Browser\":\"NewsGator FetchLinks\"}",
        "f328aa24fe1592e3e109b45bb6383490\t{\"Parent\":\"Chromium 24.0\",\"Browser_Bits\":\"64\",\"Platform\":\"Ubuntu\",\"Platform_Description\":\"Ubuntu Linux\",\"Platform_Bits\":\"64\",\"Platform_Maker\":\"Canonical Foundation\"}",
        "f32839e80b4e0b4ee638eda04456516d\t{\"Parent\":\"Baidu Browser 7.7\",\"Platform_Version\":\"4.4\",\"JavaApplets\":true,\"Device_Name\":\"Benefit M4\",\"Device_Maker\":\"ARK\",\"Device_Code_Name\":\"Benefit M4\",\"Device_Brand_Name\":\"ARK\",\"RenderingEngine_Name\":\"WebKit\",\"RenderingEngine_Description\":\"For Google Chrome, iOS (including both mobile Safari, WebViews within third-party apps, and web clips), Safari, Arora, Midori, OmniWeb, Shiira, iCab since version 4, Web, SRWare Iron, Rekonq, and in Maxthon 3.\",\"RenderingEngine_Maker\":\"Apple Inc\"}",
        "f3207f4b92dc3f0867e7f6736dab1180\t{\"Parent\":\"UC Browser 9.3\",\"Platform_Version\":\"4.1\",\"Device_Name\":\"P770\",\"Device_Maker\":\"Lenovo\",\"Device_Code_Name\":\"P770\",\"Device_Brand_Name\":\"Lenovo\",\"RenderingEngine_Name\":\"U2\",\"RenderingEngine_Description\":\"a WebKit Fork by UC Web\",\"RenderingEngine_Maker\":\"UCWeb Inc.\"}",
        "f3220bbc532c5fc42b297d2bf73f9ef7\t{\"Parent\":\"UC Browser 8.0\",\"Browser_Bits\":\"32\",\"Platform\":\"Android\",\"Platform_Description\":\"Android OS\",\"Platform_Bits\":\"32\",\"Platform_Maker\":\"Google Inc\",\"JavaApplets\":false,\"Device_Name\":\"ZenFone 5\",\"Device_Maker\":\"Asus\",\"Device_Pointing_Method\":\"touchscreen\",\"Device_Code_Name\":\"T00J\",\"Device_Brand_Name\":\"Asus\",\"RenderingEngine_Name\":\"U2\",\"RenderingEngine_Description\":\"a WebKit Fork by UC Web\",\"RenderingEngine_Maker\":\"UCWeb Inc.\"}",
        "f32a506614dbff3f7444dfd13c473584\t{\"Parent\":\"UC Browser 3.3\",\"Platform_Version\":\"5.0\",\"RenderingEngine_Name\":\"Blink\",\"RenderingEngine_Description\":\"a WebKit Fork by Google\",\"RenderingEngine_Maker\":\"Google Inc\"}",
        "f3217e406418e27f0ac326d136320412\t{\"Parent\":\"Maxthon 4.2\",\"Platform\":\"MacOSX\",\"Platform_Version\":\"10.8\",\"Platform_Description\":\"Mac OS X\",\"Platform_Maker\":\"Apple Inc\",\"Win32\":false,\"JavaApplets\":false,\"Device_Name\":\"Macintosh\",\"Device_Maker\":\"Apple Inc\",\"Device_Code_Name\":\"Macintosh\",\"Device_Brand_Name\":\"Apple\",\"RenderingEngine_Name\":\"Blink\",\"RenderingEngine_Description\":\"a WebKit Fork by Google\",\"RenderingEngine_Maker\":\"Google Inc\"}",
        "f32c64de0b312113418e67b739d79609\t{\"Parent\":\"Comodo Dragon 44.5\",\"Platform\":\"Win7\",\"Platform_Version\":\"6.1\",\"Platform_Description\":\"Windows 7\",\"Platform_Bits\":\"64\",\"Platform_Maker\":\"Microsoft Corporation\",\"Win64\":true,\"Device_Name\":\"Windows Desktop\",\"Device_Code_Name\":\"Windows Desktop\"}",
        "f323939c6bcb8d1bebea4a50f634719b\t{\"Parent\":\"Android WebView 4.3\",\"Platform_Version\":\"4.3\",\"Device_Name\":\"Galaxy Note 3 LTE\",\"Device_Maker\":\"Samsung\",\"Device_Code_Name\":\"SM-N9005\",\"Device_Brand_Name\":\"Samsung\"}",
        "f320085f2de4fe6b3ac047a97a5c3fbe\t{\"Parent\":\"Diglo 28.0\",\"Platform\":\"Win8.1\",\"Platform_Version\":\"6.3\",\"Platform_Description\":\"Windows 8.1\",\"Platform_Bits\":\"64\",\"Win32\":false,\"Win64\":true}",
        "f32574ba0edea2cb1cc580bd16ec0a2c\t{\"Parent\":\"Android WebView 2.1\",\"Platform_Version\":\"2.1\",\"Device_Name\":\"IS03\",\"Device_Maker\":\"KDDI\",\"Device_Pointing_Method\":\"unknown\",\"Device_Code_Name\":\"IS03\",\"Device_Brand_Name\":\"KDDI\"}",
        "f32e6aa0791d5dee01b424a740f1ab69\t{\"Parent\":\"Android WebView 1.5\",\"Platform_Version\":\"2.1\"}",
        "f3221daa26e39e82b61da9dd57c12cba\t{\"Parent\":\"Android WebView 1.5\",\"Platform_Version\":\"2.2\",\"Device_Name\":\"Prada 3.0\",\"Device_Maker\":\"LG\",\"Device_Pointing_Method\":\"unknown\",\"Device_Code_Name\":\"P940\",\"Device_Brand_Name\":\"LG\"}",
        "f3269432e28d766c1fb86867753d6620\t{\"Parent\":\"Android WebView 1.0\",\"Platform_Version\":\"4.0\",\"Device_Name\":\"One X\",\"Device_Maker\":\"HTC\",\"Device_Code_Name\":\"PJ83100\",\"Device_Brand_Name\":\"HTC\"}",
        "f32060322c42a71687c6ce171bc0774d\t{\"Parent\":\"Yandex Browser 15.9 for Android\",\"Platform_Version\":\"4.2\",\"Device_Name\":\"One\",\"Device_Maker\":\"HTC\",\"Device_Code_Name\":\"M7\",\"Device_Brand_Name\":\"HTC\"}",
        "f328c589f992bf00f3000059e6851e3f\t{\"Parent\":\"Yandex Browser 15.8 for Android\",\"Platform_Version\":\"4.2\",\"Device_Name\":\"A369i\",\"Device_Maker\":\"Lenovo\",\"Device_Code_Name\":\"A369i\",\"Device_Brand_Name\":\"Lenovo\"}",
        "f3263e302e96d1773999e1daff45b697\t{\"Parent\":\"Yandex Browser 1.20 for Android\",\"Platform_Version\":\"4.2\",\"isTablet\":true,\"Device_Name\":\"Uni Pad\",\"Device_Maker\":\"Verico\",\"Device_Type\":\"Tablet\",\"Device_Code_Name\":\"RP-UDM02A\",\"Device_Brand_Name\":\"Verico\"}",
        "f32c26e43ef6b1b26cc3a095c3bfe9fc\t{\"Parent\":\"Opera Mobile 9.5\",\"Device_Name\":\"P3701\",\"Device_Maker\":\"HTC\",\"Device_Pointing_Method\":\"unknown\",\"Device_Code_Name\":\"P3701\",\"Device_Brand_Name\":\"HTC\"}",
        "f32550e5dca60b8dd10c06239115a883\t{\"Parent\":\"Opera 12.17\",\"Browser_Bits\":\"32\",\"Platform\":\"WinNT\",\"Platform_Version\":\"4.0\",\"Platform_Description\":\"Windows NT\",\"Platform_Bits\":\"32\",\"Platform_Maker\":\"Microsoft Corporation\",\"Win32\":true,\"Device_Name\":\"Windows Desktop\",\"Device_Code_Name\":\"Windows Desktop\"}",
        "f32e3de75f5cc8f3f4c97b5b0bcf3bbc\t{\"Parent\":\"Opera 12.0\",\"Browser_Bits\":\"32\",\"Platform\":\"Win98\",\"Platform_Version\":\"98\",\"Platform_Description\":\"Windows 98\",\"Platform_Bits\":\"32\",\"Platform_Maker\":\"Microsoft Corporation\",\"Win32\":true,\"Device_Name\":\"Windows Desktop\",\"Device_Code_Name\":\"Windows Desktop\"}",
        "f325aedca0806bc4653736dbcfacec2b\t{\"Parent\":\"Opera 11.01\",\"Browser_Bits\":\"32\",\"Platform\":\"WinXP\",\"Platform_Version\":\"5.2\",\"Platform_Description\":\"Windows XP\",\"Platform_Bits\":\"32\",\"Platform_Maker\":\"Microsoft Corporation\",\"Win32\":true,\"Device_Name\":\"Windows Desktop\",\"Device_Code_Name\":\"Windows Desktop\"}",
        "f32bfce2489b3c5a865be9f1e730f5d5\t{\"Parent\":\"Opera 10.50\",\"Browser_Bits\":\"32\",\"Platform\":\"Linux\",\"Platform_Description\":\"Linux\",\"Platform_Bits\":\"32\",\"Platform_Maker\":\"Linux Foundation\",\"Device_Name\":\"Linux Desktop\",\"Device_Code_Name\":\"Linux Desktop\"}",
        "f3206d6393abdff5b6241accc61ff535\t{\"Parent\":\"Opera 7.53\",\"Browser_Bits\":\"32\",\"Platform\":\"MacOSX\",\"Platform_Version\":\"10\",\"Platform_Description\":\"Mac OS X\",\"Platform_Bits\":\"32\",\"Platform_Maker\":\"Apple Inc\",\"Device_Name\":\"Macintosh\",\"Device_Maker\":\"Apple Inc\",\"Device_Code_Name\":\"Macintosh\",\"Device_Brand_Name\":\"Apple\"}",
        "f32336d9fa0a2793c24ba070b9eec6a4\t{\"Parent\":\"Opera 7.03\",\"Browser_Bits\":\"32\",\"Platform\":\"Win2000\",\"Platform_Version\":\"5.0\",\"Platform_Description\":\"Windows 2000\",\"Platform_Bits\":\"32\",\"Platform_Maker\":\"Microsoft Corporation\",\"Win32\":true,\"Device_Name\":\"Windows Desktop\",\"Device_Code_Name\":\"Windows Desktop\"}",
        "f32239c51cb95d6df54ce34f4c4870d1\t{\"Parent\":\"DefaultProperties\",\"Comment\":\"Iron 44.0\",\"Browser\":\"Iron\",\"Browser_Type\":\"Browser\",\"Browser_Maker\":\"SRWare\",\"Version\":\"44.0\",\"MajorVer\":\"44\",\"Frames\":true,\"IFrames\":true,\"Tables\":true,\"Cookies\":true,\"JavaScript\":true,\"CssVersion\":\"3\",\"Device_Name\":\"general Desktop\",\"Device_Type\":\"Desktop\",\"Device_Pointing_Method\":\"mouse\",\"Device_Code_Name\":\"general Desktop\",\"RenderingEngine_Name\":\"Blink\",\"RenderingEngine_Description\":\"a WebKit Fork by Google\",\"RenderingEngine_Maker\":\"Google Inc\"}",
        "f32db6a67c40a4d797973d2a9ca680a2\t{\"Parent\":\"Iron 32.0\",\"Browser_Bits\":\"32\",\"Platform\":\"WinVista\",\"Platform_Version\":\"6.0\",\"Platform_Description\":\"Windows Vista\",\"Platform_Bits\":\"32\",\"Platform_Maker\":\"Microsoft Corporation\",\"Win32\":true,\"Device_Name\":\"Windows Desktop\",\"Device_Code_Name\":\"Windows Desktop\"}",
        "f3255b5a3a2940e922cabd912f1ce5eb\t{\"Parent\":\"Iron 8.0\",\"Browser_Bits\":\"32\",\"Platform\":\"WinXP\",\"Platform_Version\":\"5.1\",\"Platform_Description\":\"Windows XP\",\"Platform_Bits\":\"64\",\"Platform_Maker\":\"Microsoft Corporation\",\"Win64\":true,\"Device_Name\":\"Windows Desktop\",\"Device_Code_Name\":\"Windows Desktop\"}",
        "f3221fa89aca22bf87cb72d396c8e4d8\t{\"Parent\":\"Chrome 55.0 for Android\",\"Platform_Version\":\"4.0\",\"Device_Name\":\"Sensation XL with Beats Audio\",\"Device_Maker\":\"HTC\",\"Device_Pointing_Method\":\"unknown\",\"Device_Code_Name\":\"X315e\",\"Device_Brand_Name\":\"HTC\"}",
        "f3233448808dad03e57e57a021b9ea24\t{\"Parent\":\"Chrome 55.0 for Android\",\"Platform_Version\":\"5.0\"}",
        "f32c59b277eea6f902e6ebc13781840b\t{\"Parent\":\"Chrome 49.0 for Android\",\"Platform_Version\":\"4.3\",\"isTablet\":true,\"Device_Name\":\"IdeaTab S6000-F Wi-Fi, 16GB\",\"Device_Maker\":\"Lenovo\",\"Device_Type\":\"Tablet\",\"Device_Code_Name\":\"S6000L-F\",\"Device_Brand_Name\":\"Lenovo\"}",
        "f32b32a37cb6db3266bcb0ef85cbbe8b\t{\"Parent\":\"DefaultProperties\",\"Comment\":\"Chrome 45.0\",\"Browser\":\"Chrome\",\"Browser_Type\":\"Browser\",\"Browser_Bits\":\"32\",\"Browser_Maker\":\"Google Inc\",\"Version\":\"45.0\",\"MajorVer\":\"45\",\"Platform\":\"Android\",\"Platform_Description\":\"Android OS\",\"Platform_Bits\":\"32\",\"Platform_Maker\":\"Google Inc\",\"Frames\":true,\"IFrames\":true,\"Tables\":true,\"Cookies\":true,\"JavaScript\":true,\"isMobileDevice\":true,\"CssVersion\":\"3\",\"Device_Name\":\"general Mobile Phone\",\"Device_Type\":\"Mobile Phone\",\"Device_Pointing_Method\":\"touchscreen\",\"Device_Code_Name\":\"general Mobile Phone\",\"RenderingEngine_Name\":\"Blink\",\"RenderingEngine_Description\":\"a WebKit Fork by Google\",\"RenderingEngine_Maker\":\"Google Inc\"}",
        "f327ea580cde4bf2ccf867bf694bfe9c\t{\"Parent\":\"Chrome 42.0 for Android\",\"Platform_Version\":\"4.0\",\"Device_Name\":\"Galaxy S III LTE International\",\"Device_Maker\":\"Samsung\",\"Device_Code_Name\":\"GT-I9305\",\"Device_Brand_Name\":\"Samsung\"}",
        "f32fffbbbf52e3fe560202d161664b76\t{\"Parent\":\"Chrome 41.0 for Android\",\"Platform_Version\":\"4.1\",\"Device_Name\":\"Grand X\",\"Device_Maker\":\"ZTE\",\"Device_Code_Name\":\"V970\",\"Device_Brand_Name\":\"ZTE\"}",
        "f3200998c057d66b9e046b2cdf6c4fb5\t{\"Parent\":\"Chrome 38.0 for Android\",\"Platform_Version\":\"5.0\",\"Device_Name\":\"Nexus 6\",\"Device_Maker\":\"Motorola\",\"Device_Code_Name\":\"Nexus 6\",\"Device_Brand_Name\":\"Google\"}",
        "f328c3f1102b1500e5a2595dc2f42c68\t{\"Parent\":\"Chrome 35.0 for Android\",\"Platform_Version\":\"4.2\",\"Device_Name\":\"Ascend P1\",\"Device_Maker\":\"Huawei\",\"Device_Pointing_Method\":\"unknown\",\"Device_Code_Name\":\"U9200\",\"Device_Brand_Name\":\"Huawei\"}",
        "f323623220bcffb6352a989b17f464d7\t{\"Parent\":\"Chrome 34.0 for iOS\",\"Device_Name\":\"iPhone\",\"Device_Type\":\"Mobile Phone\",\"Device_Code_Name\":\"iPhone\"}",
        "f3292dfcf7db4bd88f5b91d6633696e8\t{\"Parent\":\"Chrome 30.0 for Android\",\"Platform_Version\":\"4.1\",\"Device_Name\":\"Grand X\",\"Device_Maker\":\"ZTE\",\"Device_Code_Name\":\"V970\",\"Device_Brand_Name\":\"ZTE\"}",
        "f325d455562a4ed850d739ce0fb05bfa\t{\"Parent\":\"BingPreview 1.0\",\"Browser_Bits\":\"32\",\"Platform\":\"Win7\",\"Platform_Version\":\"6.1\",\"Platform_Description\":\"Windows 7\",\"Platform_Bits\":\"32\",\"Platform_Maker\":\"Microsoft Corporation\",\"Win32\":true,\"Device_Name\":\"Windows Desktop\",\"Device_Type\":\"Desktop\",\"Device_Pointing_Method\":\"mouse\",\"Device_Code_Name\":\"Windows Desktop\"}",
        "f32d197bd2efc5ac0ce4264e30b87b4f\t{\"Parent\":\"Y!J-AGENT\"}",
        "f3267bc6c69093128e22308a643294f3\t{\"Parent\":\"Diigo Browser\",\"isTablet\":true,\"Device_Name\":\"iPad\",\"Device_Type\":\"Tablet\",\"Device_Code_Name\":\"iPad\"}",
        "f32a66f71af532639e301557f12e981b\t{\"Parent\":\"Android Browser 4.2\",\"Platform_Version\":\"2.3\",\"Device_Name\":\"B51+\",\"Device_Maker\":\"sprd\",\"Device_Code_Name\":\"B51+\",\"Device_Brand_Name\":\"sprd\"}",
        "f32dd57dd9584e293b316a2bedb4001d\t{\"Parent\":\"Android Browser 4.0\",\"Platform_Version\":\"4.3\",\"Device_Name\":\"One S\",\"Device_Maker\":\"HTC\",\"Device_Code_Name\":\"PJ401\",\"Device_Brand_Name\":\"HTC\"}",
        "f320e7952a479bbf39374dfe75a10c50\t{\"Parent\":\"Opera Mini 4.2\",\"Browser_Bits\":\"32\",\"Platform\":\"JAVA\",\"Platform_Bits\":\"32\",\"Platform_Maker\":\"Oracle\"}",
        "f323bca045816546c78a7f74d638f50c\t{\"Parent\":\"Mercury 4.0\",\"Platform_Version\":\"8.0\"}",
        "f32b47bf9249256aca7852bec2e2a195\t{\"Parent\":\"Mobile Safari Generic\",\"Platform_Version\":\"7.0\"}",
        "f32e64a284b80bdc278dc36b3859f849\t{\"Parent\":\"Instagram App 7.3 for iOS\",\"Platform_Version\":\"6.1\",\"isTablet\":true,\"Device_Name\":\"iPad\",\"Device_Type\":\"Tablet\",\"Device_Code_Name\":\"iPad\"}",
        "f32ee9ee7595fa7d7e5c1ae043a86aee\t{\"Parent\":\"Lynx\",\"Version\":\"2.4\",\"MajorVer\":\"2\",\"MinorVer\":\"4\"}",
        "f32bd8605648d163ae4a25cb8201dd83\t{\"Parent\":\"Konqueror 3.5\",\"Browser_Bits\":\"32\",\"Platform\":\"Linux\",\"Platform_Description\":\"Linux\",\"Platform_Bits\":\"32\",\"Platform_Maker\":\"Linux Foundation\",\"Device_Name\":\"Linux Desktop\",\"Device_Code_Name\":\"Linux Desktop\"}",
        "f329a785b52679d65f575d416c2c73da\t{\"Parent\":\"Lunascape 6.9\",\"Browser_Bits\":\"32\",\"Platform\":\"Win2000\",\"Platform_Version\":\"5.0\",\"Platform_Description\":\"Windows 2000\",\"Platform_Bits\":\"64\",\"Platform_Maker\":\"Microsoft Corporation\",\"Win64\":true,\"Device_Name\":\"Windows Desktop\",\"Device_Code_Name\":\"Windows Desktop\"}",
        "f32e1864243fd3491b9196101f7a834b\t{\"Parent\":\"Lunascape 4.0\",\"Browser_Bits\":\"32\",\"Platform\":\"Win8\",\"Platform_Version\":\"6.2\",\"Platform_Description\":\"Windows 8\",\"Platform_Bits\":\"32\",\"Platform_Maker\":\"Microsoft Corporation\",\"Win32\":true,\"BackgroundSounds\":true,\"VBScript\":true,\"JavaApplets\":true,\"ActiveXControls\":true,\"Device_Name\":\"Windows Desktop\",\"Device_Code_Name\":\"Windows Desktop\",\"RenderingEngine_Name\":\"Trident\",\"RenderingEngine_Description\":\"For Internet Explorer since version 4.0 and embedded WebBrowser controls (such as Internet Explorer shells, Maxthon and some media players).\",\"RenderingEngine_Maker\":\"Microsoft Corporation\"}",
        "f32baea28417ed5108cef75bf09ee3da\t{\"Parent\":\"Palemoon 25.0\",\"Browser_Bits\":\"32\",\"Platform\":\"WinXP\",\"Platform_Version\":\"5.2\",\"Platform_Description\":\"Windows XP\",\"Platform_Bits\":\"32\",\"Platform_Maker\":\"Microsoft Corporation\",\"Win32\":true,\"Device_Name\":\"Windows Desktop\",\"Device_Code_Name\":\"Windows Desktop\"}",
        "f321cf503b631f3384726e64667620c9\t{\"Parent\":\"Palemoon Generic\",\"Browser_Bits\":\"32\",\"Platform\":\"Linux\",\"Platform_Description\":\"Linux\",\"Platform_Bits\":\"32\",\"Platform_Maker\":\"Linux Foundation\",\"JavaApplets\":true,\"Device_Name\":\"Linux Desktop\",\"Device_Code_Name\":\"Linux Desktop\",\"RenderingEngine_Name\":\"Gecko\",\"RenderingEngine_Description\":\"For Firefox, Camino, K-Meleon, SeaMonkey, Netscape, and other Gecko-based browsers.\",\"RenderingEngine_Maker\":\"Mozilla Foundation\"}",
        "f324f13077f215cebc28f7d50e3c74f0\t{\"Parent\":\"Fennec 18.0\",\"Device_Pointing_Method\":\"unknown\"}",
        "f32905ffb12b73cdcd3a7e404f303095\t{\"Parent\":\"Waterfox 28.0\",\"Platform\":\"Win10\",\"Platform_Version\":\"10.0\",\"Platform_Description\":\"Windows 10\",\"Platform_Bits\":\"64\",\"Win32\":false,\"Win64\":true}",
        "f3223f33045bc6ce8dec890bac62960c\t{\"Parent\":\"ESPN Radio 4.5\",\"Platform_Version\":\"7.1\"}",
        "f32478110706bc5463c0e49da4acda6f\t{\"Parent\":\"ESPN Radio 3.2\",\"Platform_Version\":\"7.0\"}"
    ]
}