{
    "content": [
        "ad6525b0f149bb63080a76c2ad96d24a\t{\"Parent\":\"SEO \\u0026 Analytics\",\"Browser\":\"SiteExplorer\",\"Browser_Maker\":\"siteexplorer.info\",\"Version\":\"1.0b\",\"MajorVer\":\"1\",\"MinorVer\":\"0b\",\"Beta\":true}",
        "ad6c23c343344ae27711ef77fa5599eb\t{\"Parent\":\"Chromium 10.0\",\"Platform\":\"Ubuntu\",\"Platform_Description\":\"Ubuntu Linux\",\"Platform_Maker\":\"Canonical Foundation\"}",
        "ad6cebd83966fb9918eb476298df843a\t{\"Parent\":\"Coc Coc Browser 61.0\",\"Platform\":\"WinVista\",\"Platform_Version\":\"6.0\",\"Platform_Description\":\"Windows Vista\"}",
        "ad6737992ccb5d6a683565a0fed74812\t{\"Parent\":\"UC Browser 11.2 for Android\",\"Platform_Version\":\"4.3\",\"Device_Name\":\"Galaxy S III\",\"Device_Maker\":\"Samsung\",\"Device_Code_Name\":\"GT-I9300\",\"Device_Brand_Name\":\"Samsung\"}",
        "ad6fd4c2d45c6f382027f7289990a78c\t{\"Parent\":\"UC Browser 10.1 for Android\",\"RenderingEngine_Name\":\"U2\"}",
        "ad62ba23717f62f1248550927ad0ffdd\t{\"Parent\":\"UC Browser 11.0 for iOS\",\"Browser_Modus\":\"Chrome\",\"Platform_Version\":\"11.0\",\"Device_Name\":\"iPhone\",\"Device_Type\":\"Mobile Phone\",\"Device_Code_Name\":\"iPhone\"}",
        "ad6edf501d203d68df0c94b4a27ebeca\t{\"Parent\":\"Avant 2013\",\"Browser_Bits\":\"64\",\"Platform\":\"Win7\",\"Platform_Version\":\"6.1\",\"Platform_Description\":\"Windows 7\",\"Platform_Bits\":\"64\",\"Platform_Maker\":\"Microsoft Corporation\",\"Win64\":true,\"RenderingEngine_Version\":\"26.0\"}",
        "ad6ce276d441dc64380f0938fa0453f0\t{\"Parent\":\"UC Browser 2.4 for Android\"}",
        "ad6b8b973babb7677b40c27476308fc8\t{\"Parent\":\"Maxthon Generic\",\"Platform\":\"Win8.1\",\"Platform_Version\":\"6.3\",\"Platform_Description\":\"Windows 8.1\",\"Platform_Bits\":\"64\",\"Win32\":false,\"Win64\":true}",
        "ad639f9d16412611ef8e96342aac656d\t{\"Parent\":\"Comodo Dragon 11.0\",\"Platform\":\"WinXP\",\"Platform_Version\":\"5.1\",\"Platform_Description\":\"Windows XP\",\"Platform_Bits\":\"64\",\"Win32\":false,\"Win64\":true}",
        "ad63a80f3072af36e67e43938aff24e8\t{\"Parent\":\"Android WebView 65.0\",\"Platform_Version\":\"5.1\",\"Device_Name\":\"Galaxy S5 Mini (AT\\u0026T)\",\"Device_Maker\":\"Samsung\",\"Device_Code_Name\":\"SM-G800A\",\"Device_Brand_Name\":\"Samsung\"}",
        "ad6d5c1312382c0a8acdb4645ccbea28\t{\"Parent\":\"Android WebView 43.0\",\"Platform_Version\":\"7.0\"}",
        "ad60ffbb9af683681889b81b7990bedf\t{\"Parent\":\"Samsung Browser 6.4\",\"Platform_Version\":\"5.0\",\"isTablet\":true,\"Device_Name\":\"Galaxy Tab 4 10.1 16GB\",\"Device_Maker\":\"Samsung\",\"Device_Type\":\"Tablet\",\"Device_Code_Name\":\"SM-T530NU\",\"Device_Brand_Name\":\"Samsung\"}",
        "ad673d4a89727b8bbd8a503b931d5d7e\t{\"Parent\":\"Android WebView 42.0\",\"Platform_Version\":\"4.0\",\"Device_Name\":\"One M7\",\"Device_Maker\":\"HTC\",\"Device_Code_Name\":\"M7\",\"Device_Brand_Name\":\"HTC\"}",
        "ad6bbe5f41cb8b3bdcbf5ab0799764df\t{\"Parent\":\"Android WebView 32.0\",\"Platform_Version\":\"4.4\",\"Device_Name\":\"Canvas Gold\",\"Device_Maker\":\"Micromax\",\"Device_Code_Name\":\"A300\",\"Device_Brand_Name\":\"Micromax\"}",
        "ad69541388113612e9e218dea0382695\t{\"Parent\":\"Samsung Browser 5.4\",\"Platform_Version\":\"5.1\",\"Device_Name\":\"Galaxy S6 (LATAM, Singapore, India, Australia)\",\"Device_Maker\":\"Samsung\",\"Device_Code_Name\":\"SM-G920I\",\"Device_Brand_Name\":\"Samsung\"}",
        "ad696029055c38b698618a36756f0983\t{\"Parent\":\"QQBrowser 7.7 for Android\",\"Browser_Bits\":\"32\",\"Platform\":\"Android\",\"Platform_Version\":\"4.4\",\"Platform_Description\":\"Android OS\",\"Platform_Bits\":\"32\",\"Platform_Maker\":\"Google Inc\"}",
        "ad6983593346a45fd6dba5c9e7127dbd\t{\"Parent\":\"QQBrowser 6.0 for Android\",\"Browser_Bits\":\"32\",\"Platform\":\"Android\",\"Platform_Description\":\"Android OS\",\"Platform_Bits\":\"32\",\"Platform_Maker\":\"Google Inc\",\"JavaApplets\":true,\"Device_Name\":\"Alpha a5000\",\"Device_Maker\":\"Sony\",\"Device_Type\":\"Digital Camera\",\"Device_Code_Name\":\"A5000\",\"Device_Brand_Name\":\"Sony\",\"RenderingEngine_Name\":\"WebKit\",\"RenderingEngine_Description\":\"For Google Chrome, iOS (including both mobile Safari, WebViews within third-party apps, and web clips), Safari, Arora, Midori, OmniWeb, Shiira, iCab since version 4, Web, SRWare Iron, Rekonq, and in Maxthon 3.\",\"RenderingEngine_Maker\":\"Apple Inc\"}",
        "ad693e5395256bbd88bcb4794a89a92b\t{\"Parent\":\"Flixster App 7.2\",\"Platform_Version\":\"10.3\",\"Device_Name\":\"iPhone\",\"Device_Type\":\"Mobile Phone\",\"Device_Code_Name\":\"iPhone\"}",
        "ad6b524b9cfbdf3cd73d6b064cf3d8ac\t{\"Parent\":\"Yandex Browser 17.7 for iOS\",\"Platform_Version\":\"9.1\",\"Device_Name\":\"iPod Touch\",\"Device_Code_Name\":\"iPod Touch\"}",
        "ad683fc5b6c76dbe5de19672b140341a\t{\"Parent\":\"Yandex Browser 17.6 for iOS\",\"Platform_Version\":\"8.4\",\"Device_Name\":\"iPod Touch\",\"Device_Code_Name\":\"iPod Touch\"}",
        "ad67812296231190476f33c0d4a4507d\t{\"Parent\":\"Yandex Browser 14.5 for Android\",\"Platform_Version\":\"4.2\",\"Device_Name\":\"A526\",\"Device_Maker\":\"Lenovo\",\"Device_Code_Name\":\"A526\",\"Device_Brand_Name\":\"Lenovo\"}",
        "ad60363eac0725bc63e8b1bb8f1a67ea\t{\"Parent\":\"Yandex Browser 13.12 for Android\",\"Platform_Version\":\"4.4\",\"Device_Name\":\"One Touch Pop 2\",\"Device_Maker\":\"Alcatel\",\"Device_Code_Name\":\"OT-5042D\",\"Device_Brand_Name\":\"Alcatel\"}",
        "ad67299df499556d2295d6ad1d918a14\t{\"Parent\":\"Yandex Browser 14.12 for iOS\",\"isTablet\":true,\"Device_Name\":\"iPad\",\"Device_Type\":\"Tablet\",\"Device_Code_Name\":\"iPad\"}",
        "ad6bf99d30409ead6cb23c036fd0a345\t{\"Parent\":\"Opera Mobile 40.0 for Android\",\"Platform_Version\":\"6.0\",\"Device_Name\":\"G5 (Verizon)\",\"Device_Maker\":\"LG\",\"Device_Code_Name\":\"VS987\",\"Device_Brand_Name\":\"LG\"}",
        "ad626e87de6ef42933099170aac6703b\t{\"Parent\":\"Opera Mobile 35.0 for Android\",\"Platform_Version\":\"4.4\",\"Device_Name\":\"G2\",\"Device_Maker\":\"LG\",\"Device_Code_Name\":\"D802\",\"Device_Brand_Name\":\"LG\"}",
        "ad6eb270fb6b5702e14670ff6a575dec\t{\"Parent\":\"Opera Mobile 28.0 for Android\",\"Platform_Version\":\"4.2\",\"Device_Name\":\"Note 3 Super Slim\",\"Device_Maker\":\"Star\",\"Device_Code_Name\":\"N3+\",\"Device_Brand_Name\":\"Star\"}",
        "ad6e61e1faf19552a4ba9a88106d6776\t{\"Parent\":\"Opera 10.63\",\"Browser_Bits\":\"32\",\"Platform\":\"MacOSX\",\"Platform_Version\":\"10.4\",\"Platform_Description\":\"Mac OS X\",\"Platform_Bits\":\"32\",\"Platform_Maker\":\"Apple Inc\",\"Device_Name\":\"Macintosh\",\"Device_Maker\":\"Apple Inc\",\"Device_Code_Name\":\"Macintosh\",\"Device_Brand_Name\":\"Apple\"}",
        "ad63af1ca9cb12d8a4e9441a74de6f9c\t{\"Parent\":\"Opera 9.61\",\"Browser_Bits\":\"32\",\"Platform\":\"WinVista\",\"Platform_Version\":\"6.0\",\"Platform_Description\":\"Windows Vista\",\"Platform_Bits\":\"64\",\"Platform_Maker\":\"Microsoft Corporation\",\"Win64\":true}",
        "ad6c24f0433d9249a74813023fb5997d\t{\"Parent\":\"Opera 9.52\",\"Browser_Bits\":\"32\",\"Platform\":\"Linux\",\"Platform_Description\":\"Linux\",\"Platform_Bits\":\"32\",\"Platform_Maker\":\"Linux Foundation\",\"Device_Name\":\"Linux Desktop\",\"Device_Code_Name\":\"Linux Desktop\"}",
        "ad6315de4465c4ec9c35264c46b595ac\t{\"Parent\":\"Opera 9.4\",\"Browser_Bits\":\"32\",\"Platform\":\"MacOSX\",\"Platform_Version\":\"10.4\",\"Platform_Description\":\"Mac OS X\",\"Platform_Bits\":\"32\",\"Platform_Maker\":\"Apple Inc\",\"Device_Name\":\"Macintosh\",\"Device_Maker\":\"Apple Inc\",\"Device_Code_Name\":\"Macintosh\",\"Device_Brand_Name\":\"Apple\"}",
        "ad66e129ee60b90cbaeec2687b3f69fb\t{\"Parent\":\"Opera 7.20\",\"Browser_Bits\":\"32\",\"Platform\":\"WinXP\",\"Platform_Version\":\"5.2\",\"Platform_Description\":\"Windows XP\",\"Platform_Bits\":\"32\",\"Platform_Maker\":\"Microsoft Corporation\",\"Win32\":true}",
        "ad68717de3a249c288d1c16b57ec8b3f\t{\"Parent\":\"Opera 6.11\",\"Browser_Bits\":\"32\",\"Platform\":\"Win8\",\"Platform_Version\":\"6.2\",\"Platform_Description\":\"Windows 8\",\"Platform_Bits\":\"64\",\"Platform_Maker\":\"Microsoft Corporation\",\"Win64\":true}",
        "ad6a42a1631abcdbf1c4bb85cd7804c3\t{\"Parent\":\"Opera 6.0\",\"Browser_Bits\":\"64\",\"Platform\":\"Win7\",\"Platform_Version\":\"6.1\",\"Platform_Description\":\"Windows 7\",\"Platform_Bits\":\"64\",\"Platform_Maker\":\"Microsoft Corporation\",\"Win64\":true}",
        "ad6e0cd8ff4406d2b83f797befd05178\t{\"Parent\":\"Google App Engine\",\"Browser_Bits\":\"32\",\"Platform\":\"Win8.1\",\"Platform_Version\":\"6.3\",\"Platform_Description\":\"Windows 8.1\",\"Platform_Bits\":\"32\",\"Platform_Maker\":\"Microsoft Corporation\",\"Win32\":true}",
        "ad64a3d68dc98ec08d07bbe079022602\t{\"Parent\":\"Edge 41.0 for iOS\",\"Platform_Version\":\"9.2\",\"Device_Name\":\"iPhone\",\"Device_Type\":\"Mobile Phone\",\"Device_Code_Name\":\"iPhone\"}",
        "ad604c9ebd2775c02b9dca95981c34df\t{\"Parent\":\"Chrome 70.0 for Android\",\"Platform_Version\":\"4.4\",\"isTablet\":true,\"Device_Name\":\"Galaxy Note 10.1 LTE\",\"Device_Maker\":\"Samsung\",\"Device_Type\":\"Tablet\",\"Device_Code_Name\":\"GT-N8020\",\"Device_Brand_Name\":\"Samsung\"}",
        "ad64b1be0c7b3297f6448d3808553b5d\t{\"Parent\":\"Chrome 67.0 for Android\",\"Platform_Version\":\"4.1\",\"Device_Name\":\"Xperia Ion\",\"Device_Maker\":\"SonyEricsson\",\"Device_Code_Name\":\"LT28h\",\"Device_Brand_Name\":\"SonyEricsson\"}",
        "ad6dcbe2f5e313d9b652f64cf2a8c892\t{\"Parent\":\"Chrome 66.0 for Android\",\"Platform_Version\":\"8.0\",\"Device_Name\":\"Mi Mix 2\",\"Device_Maker\":\"Xiaomi Tech\",\"Device_Code_Name\":\"Mi Mix 2\",\"Device_Brand_Name\":\"Xiaomi\"}",
        "ad60a8f4afb89780985f6ec9306b6e34\t{\"Parent\":\"Chrome 65.0 for Android\",\"Platform_Version\":\"4.4\",\"Device_Name\":\"Vivo IV\",\"Device_Maker\":\"BLU\",\"Device_Code_Name\":\"Vivo IV\",\"Device_Brand_Name\":\"BLU\"}",
        "ad6f0ae7e51bd685df4284d6d3745b52\t{\"Parent\":\"Chrome 63.0 for Android\",\"Platform_Version\":\"6.0\",\"Device_Name\":\"Galaxy A5 (Peru, Colombia)\",\"Device_Maker\":\"Samsung\",\"Device_Code_Name\":\"SM-A500M\",\"Device_Brand_Name\":\"Samsung\"}",
        "ad658bd6931a9706835bbc165e4d5485\t{\"Parent\":\"Chrome 59.0 for Android\",\"Platform_Version\":\"4.1\",\"Device_Name\":\"Droid DNA\",\"Device_Maker\":\"HTC\",\"Device_Code_Name\":\"HTC6435LVW\",\"Device_Brand_Name\":\"HTC\"}",
        "ad6200540387143e922f029650c335ec\t{\"Parent\":\"Chrome 54.0 for Android\",\"Platform_Version\":\"6.0\",\"Device_Name\":\"Nexus 6P\",\"Device_Maker\":\"Huawei\",\"Device_Code_Name\":\"Nexus 6P\",\"Device_Brand_Name\":\"Google\"}",
        "ad6fc8bd4f7bd326a1180fd3290d4715\t{\"Parent\":\"Chrome 51.0 for Android\",\"Platform_Version\":\"4.2\",\"Device_Name\":\"One X\",\"Device_Maker\":\"HTC\",\"Device_Code_Name\":\"PJ83100\",\"Device_Brand_Name\":\"HTC\"}",
        "ad610cd7f67244da9aeecc154fde0d34\t{\"Parent\":\"Chrome 47.0 for Android\",\"Platform_Version\":\"4.4\",\"Device_Name\":\"Xperia M\",\"Device_Maker\":\"Sony\",\"Device_Code_Name\":\"C1905\",\"Device_Brand_Name\":\"Sony\"}",
        "ad6cbed4fb45540fc34b6934afdf1d08\t{\"Parent\":\"Chrome 44.0 for Android\",\"Platform_Version\":\"4.2\",\"Device_Name\":\"Galaxy Mega 6.3\",\"Device_Maker\":\"Samsung\",\"Device_Code_Name\":\"GT-I9205\",\"Device_Brand_Name\":\"Samsung\"}",
        "ad696355481bbda7c966426754865559\t{\"Parent\":\"Chrome 35.0\",\"Browser_Bits\":\"32\",\"Platform\":\"Win10\",\"Platform_Version\":\"10.0\",\"Platform_Description\":\"Windows 10\",\"Platform_Bits\":\"32\",\"Platform_Maker\":\"Microsoft Corporation\",\"Win32\":true,\"isAnonymized\":true}",
        "ad6e3b28765192d0ef6e538a9b5de686\t{\"Parent\":\"Chrome 40.0 for Android\",\"Platform_Version\":\"4.4\",\"isTablet\":true,\"Device_Name\":\"Galaxy Tab 4 8.0 4G (Verizon)\",\"Device_Maker\":\"Samsung\",\"Device_Type\":\"Tablet\",\"Device_Code_Name\":\"SM-T337V\",\"Device_Brand_Name\":\"Samsung\"}",
        "ad646f5fc153baddac04d0f4873a3130\t{\"Parent\":\"Chrome 37.0 for Android\",\"Platform_Version\":\"4.0\",\"Device_Name\":\"Nexus S\",\"Device_Maker\":\"Samsung\",\"Device_Code_Name\":\"Nexus S\",\"Device_Brand_Name\":\"Google\"}",
        "ad6bebe52004e2af604842d8b6eb3569\t{\"Parent\":\"Chrome 35.0 for Android\",\"Platform_Version\":\"4.2\",\"isTablet\":true,\"Device_Name\":\"MultiPad 4 Diamond 10.1 3G\",\"Device_Maker\":\"Prestigio\",\"Device_Type\":\"Tablet\",\"Device_Code_Name\":\"PMP7110D3G\",\"Device_Brand_Name\":\"Prestigio\"}",
        "ad66caa50fbe0eddaf6fa15ff1c7db4d\t{\"Parent\":\"Chrome 34.0 for Android\",\"Platform_Version\":\"4.0\",\"Device_Name\":\"Galaxy Note II\",\"Device_Maker\":\"Samsung\",\"Device_Code_Name\":\"SCH-I605\",\"Device_Brand_Name\":\"Samsung\"}",
        "ad6144e8554ab5a481d421da46144c51\t{\"Parent\":\"Chrome 32.0 for Android\",\"Platform_Version\":\"4.4\",\"Device_Name\":\"Galaxy S5 LTE\",\"Device_Maker\":\"Samsung\",\"Device_Code_Name\":\"SM-G900F\",\"Device_Brand_Name\":\"Samsung\"}",
        "ad642920a8bcd2c24a98fe304440d690\t{\"Parent\":\"Chrome 30.0 for Android\",\"Platform_Version\":\"5.0\",\"Device_Name\":\"Galaxy A5 (Peru, Colombia)\",\"Device_Maker\":\"Samsung\",\"Device_Code_Name\":\"SM-A500M\",\"Device_Brand_Name\":\"Samsung\"}",
        "ad60dc6e7fa222fa6e54393a4efca8af\t{\"Parent\":\"Chrome 26.0 for Android\",\"Platform_Version\":\"4.1\",\"isTablet\":true,\"Device_Name\":\"Transformer Pad TF300T\",\"Device_Maker\":\"Asus\",\"Device_Type\":\"Tablet\",\"Device_Code_Name\":\"TF300T\",\"Device_Brand_Name\":\"Asus\"}",
        "ad6ec79e70717cff02dd0d455a158a1c\t{\"Parent\":\"Chrome 18.0 for Android\",\"Platform_Version\":\"4.1\",\"isTablet\":true,\"Device_Name\":\"Eee Pad Transformer TF101\",\"Device_Maker\":\"Asus\",\"Device_Type\":\"Tablet\",\"Device_Code_Name\":\"TF101\",\"Device_Brand_Name\":\"Asus\"}",
        "ad6680b2469ae71fd9db184bc9bcffaf\t{\"Parent\":\"Chrome 62.0 for iOS\",\"Platform_Version\":\"10.2\",\"Device_Name\":\"iPod Touch\",\"Device_Code_Name\":\"iPod Touch\"}",
        "ad6a6a7b1ef4679b7fbb618cd78890a3\t{\"Parent\":\"Microsoft Office 2016\",\"Browser_Bits\":\"32\",\"Platform\":\"WinXP\",\"Platform_Version\":\"5.2\",\"Platform_Description\":\"Windows XP\",\"Platform_Bits\":\"64\",\"Platform_Maker\":\"Microsoft Corporation\",\"Win64\":true,\"CssVersion\":\"3\",\"RenderingEngine_Version\":\"7.0\"}",
        "ad6105142f4f579780cdcfaf7fb10d6b\t{\"Parent\":\"Ntent Browser 3.2\",\"Browser_Bits\":\"32\",\"Platform\":\"Android\",\"Platform_Version\":\"6.0\",\"Platform_Description\":\"Android OS\",\"Platform_Bits\":\"32\",\"Platform_Maker\":\"Google Inc\",\"JavaApplets\":true,\"Device_Name\":\"Galaxy J5 Metal Duos\",\"Device_Maker\":\"Samsung\",\"Device_Code_Name\":\"SM-J510MN\",\"Device_Brand_Name\":\"Samsung\",\"RenderingEngine_Name\":\"WebKit\",\"RenderingEngine_Description\":\"For Google Chrome, iOS (including both mobile Safari, WebViews within third-party apps, and web clips), Safari, Arora, Midori, OmniWeb, Shiira, iCab since version 4, Web, SRWare Iron, Rekonq, and in Maxthon 3.\",\"RenderingEngine_Maker\":\"Apple Inc\"}",
        "ad68eccec3667c80b3c68aa088a36b0b\t{\"Parent\":\"Mercury 8.8\",\"Platform_Version\":\"9.0\",\"Device_Name\":\"iPhone\",\"Device_Type\":\"Mobile Phone\",\"Device_Code_Name\":\"iPhone\"}",
        "ad6d675d40dae1b059837c1dcd290069\t{\"Parent\":\"Mercury Generic\",\"Platform_Version\":\"8.4\"}",
        "ad6ea799de332d3f5c71f0589f0feb34\t{\"Parent\":\"Instagram App 13.0 for Android\",\"Platform_Version\":\"4.4\",\"isTablet\":true,\"Device_Name\":\"Ideatab A8-50 WI-FI + 3G\",\"Device_Maker\":\"Lenovo\",\"Device_Type\":\"Tablet\",\"Device_Code_Name\":\"A5500-HV\",\"Device_Brand_Name\":\"Lenovo\"}",
        "ad685829125436b3799f32ce4b9d8cdc\t{\"Parent\":\"Instagram App 9.0 for Android\",\"Platform_Version\":\"4.4\",\"Device_Name\":\"Studio 5.5 k\",\"Device_Maker\":\"BLU\",\"Device_Code_Name\":\"D710\",\"Device_Brand_Name\":\"BLU\"}",
        "ad6ae703a44e2d425c84d027d7dc6d60\t{\"Parent\":\"Electron 1.4\",\"Browser_Bits\":\"32\",\"Platform\":\"MacOSX\",\"Platform_Version\":\"10.9\",\"Platform_Description\":\"Mac OS X\",\"Platform_Bits\":\"32\",\"Platform_Maker\":\"Apple Inc\",\"Device_Name\":\"Macintosh\",\"Device_Maker\":\"Apple Inc\",\"Device_Code_Name\":\"Macintosh\",\"Device_Brand_Name\":\"Apple\"}",
        "ad6e326bb06f81f4c8de1362f5851056\t{\"Parent\":\"Camino 1.4\",\"Platform_Version\":\"10.8\"}",
        "ad60c57cbc48aa7211928885aa3d8ed0\t{\"Parent\":\"Camino 0.8\",\"Platform_Version\":\"10.6\"}",
        "ad6843859ceb17ad4284095e90613861\t{\"Parent\":\"Lunascape 2.1\",\"Platform\":\"WinXP\",\"Platform_Version\":\"5.2\",\"Platform_Description\":\"Windows XP\",\"Platform_Bits\":\"64\",\"Win32\":false,\"Win64\":true,\"RenderingEngine_Version\":\"4.0\"}",
        "ad6398512a218b2f624167d70a0c1b7a\t{\"Parent\":\"PaleMoon 20.1\",\"Browser_Bits\":\"32\",\"Platform\":\"Win10\",\"Platform_Version\":\"6.4\",\"Platform_Description\":\"Windows 10\",\"Platform_Bits\":\"64\",\"Platform_Maker\":\"Microsoft Corporation\",\"Win64\":true}",
        "ad6ac6d4662d4787bb44866c562edf63\t{\"Parent\":\"SeaMonkey 2.11\",\"Browser_Bits\":\"64\",\"Platform\":\"Linux\",\"Platform_Description\":\"Linux\",\"Platform_Bits\":\"64\",\"Platform_Maker\":\"Linux Foundation\",\"Device_Name\":\"Linux Desktop\",\"Device_Code_Name\":\"Linux Desktop\"}",
        "ad65137ef868906f805067941ed396eb\t{\"Parent\":\"SeaMonkey 2.10\",\"Browser_Bits\":\"32\",\"Platform\":\"WinXP\",\"Platform_Version\":\"5.2\",\"Platform_Description\":\"Windows XP\",\"Platform_Bits\":\"64\",\"Platform_Maker\":\"Microsoft Corporation\",\"Win64\":true}",
        "ad6fc4e52a3493ee6ba7ab926ae037af\t{\"Parent\":\"Waterfox 41.0\",\"Browser_Bits\":\"32\",\"Platform\":\"MacOSX\",\"Platform_Version\":\"10.5\",\"Platform_Description\":\"Mac OS X\",\"Platform_Bits\":\"32\",\"Platform_Maker\":\"Apple Inc\",\"Device_Name\":\"Macintosh\",\"Device_Maker\":\"Apple Inc\",\"Device_Code_Name\":\"Macintosh\",\"Device_Brand_Name\":\"Apple\"}",
        "ad6a461770351575a0976401aec68b5b\t{\"Parent\":\"Firefox 52.0\",\"Browser_Bits\":\"32\",\"Platform\":\"SunOS\",\"Platform_Description\":\"SunOS\",\"Platform_Bits\":\"32\",\"Platform_Maker\":\"Oracle\",\"Device_Name\":\"general Desktop\",\"Device_Code_Name\":\"general Desktop\"}",
        "ad6bc7f7a7750a7754e41f0af4d58a25\t{\"Parent\":\"Firefox 22.0\",\"Browser_Bits\":\"64\",\"Platform\":\"NetBSD\",\"Platform_Description\":\"NetBSD\",\"Platform_Bits\":\"64\",\"Device_Name\":\"general Desktop\",\"Device_Code_Name\":\"general Desktop\"}",
        "ad6c74ecd6dc866820de9093f8b1b110\t{\"Parent\":\"Firefox 20.0\",\"Browser_Bits\":\"32\",\"Platform\":\"WinXP\",\"Platform_Version\":\"5.1\",\"Platform_Description\":\"Windows XP\",\"Platform_Bits\":\"32\",\"Platform_Maker\":\"Microsoft Corporation\",\"Win32\":true}",
        "ad69b5cd82d02f44a29bf9e5303b9e4e\t{\"Parent\":\"Firefox 17.0\",\"Browser_Bits\":\"64\",\"Platform\":\"FreeBSD\",\"Platform_Description\":\"FreeBSD\",\"Platform_Bits\":\"64\",\"Platform_Maker\":\"FreeBSD Foundation\",\"Device_Name\":\"general Desktop\",\"Device_Code_Name\":\"general Desktop\"}",
        "ad6335c6dd880a1a6366f5602a331dee\t{\"Parent\":\"Firefox 10.0\",\"Browser_Bits\":\"32\",\"Platform\":\"OpenBSD\",\"Platform_Description\":\"OpenBSD\",\"Platform_Bits\":\"32\",\"Device_Name\":\"general Desktop\",\"Device_Code_Name\":\"general Desktop\"}",
        "ad613a478f230e107c293a3e5c544d5d\t{\"Parent\":\"Palm Source\",\"Browser_Bits\":\"32\",\"Platform\":\"Win98\",\"Platform_Version\":\"98\",\"Platform_Description\":\"Windows 98\",\"Platform_Bits\":\"32\",\"Platform_Maker\":\"Microsoft Corporation\",\"Win32\":true}"
    ]
}
